{
  "name": "PROJECT_IMAGE_STORAGE/880073484-File: datauser0com.example.oshikatsu_productcache4c67a721-87fa-4f4d-b317-cd5cfc6be0661000000033.png",
  "bucket": "oshikatsu-dev-8bb0d.appspot.com",
  "metageneration": 1,
  "generation": 1709821409452,
  "contentType": "application/octet-stream",
  "storageClass": "STANDARD",
  "contentDisposition": "inline",
  "downloadTokens": [
    "6d017971-69e3-4096-b511-533e83a68047"
  ],
  "etag": "zbpQqEpa5S1ACaFwukjLMYTPFJw",
  "customMetadata": {},
  "timeCreated": "2024-03-07T14:23:29.452Z",
  "updated": "2024-03-07T14:23:29.452Z",
  "size": 3963611,
  "md5Hash": "7hIJRqSPcCOA7VVQy32HXA==",
  "crc32c": "953200811"
}